graph_force-0.2.2.dist-info/METADATA
graph_force-0.2.2.dist-info/WHEEL
graph_force/__init__.py
graph_force/graph_force.cpython-311-x86_64-linux-gnu.so
graph_force-0.2.2.dist-info/RECORD
