Metadata-Version: 2.1
Name: graph_force
Version: 0.2.2
Classifier: Programming Language :: Rust
Classifier: Programming Language :: Python :: Implementation :: CPython
Classifier: Programming Language :: Python :: Implementation :: PyPy
Classifier: Topic :: Scientific/Engineering :: Visualization
Classifier: License :: OSI Approved :: MIT License
Summary: A library for embedding graphs in 2D space, using force-directed layouts.
Keywords: graph,layout,force-directed
Author-email: Niko Abeler <niko@rerere.org>
Maintainer-email: Niko Abeler <niko@rerere.org>
Requires-Python: >=3.11
Project-URL: homepage, https://github.com/H4kor/graph-force/
Project-URL: repository, https://github.com/H4kor/graph-force/
